server_cli/__init__.py
server_cli/server.py
server_cli-1.0.3.dist-info/LICENSE
server_cli-1.0.3.dist-info/METADATA
server_cli-1.0.3.dist-info/WHEEL
server_cli-1.0.3.dist-info/entry_points.txt
server_cli-1.0.3.dist-info/top_level.txt
server_cli-1.0.3.dist-info/RECORD
