Metadata-Version: 2.1
Name: server-cli
Version: 1.0.3
Summary: A server management tool which helps you memorize ssh command
Home-page: https://github.com/yjxkwp/server-cli
Author: kwp
Author-email: i@emmm.wtf
License: MIT
Platform: UNKNOWN
Classifier: License :: OSI Approved :: MIT License
Classifier: Programming Language :: Python :: 3
Classifier: Programming Language :: Python :: 3.4
Classifier: Programming Language :: Python :: 3.5
Classifier: Programming Language :: Python :: 3.6
Classifier: Programming Language :: Python :: 3.7
Requires-Python: >=3.5, <4
Requires-Dist: PrettyTable
Requires-Dist: ping3
